namehash.py
ens_namehash-1.0.0.dist-info/DESCRIPTION.rst
ens_namehash-1.0.0.dist-info/METADATA
ens_namehash-1.0.0.dist-info/RECORD
ens_namehash-1.0.0.dist-info/WHEEL
ens_namehash-1.0.0.dist-info/metadata.json
ens_namehash-1.0.0.dist-info/top_level.txt
